{
  "ya": {
    "id": "ya",
    "name": "雅",
    "type": "resident",
    "interactions": [
      {"id": "chat", "label": "聊天"},
      {"id": "order", "label": "点单"},
      {"id": "gift", "label": "送礼"},
      {"id": "leave", "label": "离开"}
    ]
  },
  "jing": {
    "id": "jing",
    "name": "静",
    "type": "resident",
    "interactions": [
      {"id": "chat", "label": "聊天"},
      {"id": "study", "label": "补习"},
      {"id": "gift", "label": "送礼"},
      {"id": "leave", "label": "离开"}
    ]
  }
}
